MANIFEST.in
README.md
ordered_uuid.py
setup.py
python_ordered_uuid.egg-info/PKG-INFO
python_ordered_uuid.egg-info/SOURCES.txt
python_ordered_uuid.egg-info/dependency_links.txt
python_ordered_uuid.egg-info/top_level.txt