Metadata-Version: 1.1
Name: python-ordered-uuid
Version: 1.3.5
Summary: A python implementation of Ordered UUID.
Home-page: https://github.com/pawl/python-ordered-uuid
Author: Paul Brown
Author-email: paul90brown+pypi@gmail.com
License: UNKNOWN
Platform: UNKNOWN
Classifier: Programming Language :: Python :: 2
Classifier: Programming Language :: Python :: 3
